[
  {
    "id": 1,
    "item_prop": "",
    "container_id": 1
  },
  {
    "id": 2,
    "item_prop": "uchredLaw",
    "container_id": 2
  },
  {
    "id": 3,
    "item_prop": "filInfo",
    "container_id": 3
  },
  {
    "id": 4,
    "item_prop": "repInfo",
    "container_id": 4
  },
  {
    "id": 5,
    "item_prop": "structOrgUprav",
    "container_id": 5
  },
  {
    "id": 6,
    "item_prop": "",
    "container_id": 6
  },
  {
    "id": 7,
    "item_prop": "eduAccred",
    "container_id": 7
  },
  {
    "id": 8,
    "item_prop": "eduPOAccred",
    "container_id": 8
  },
  {
    "id": 9,
    "item_prop": "eduChislen",
    "container_id": 9
  },
  {
    "id": 10,
    "item_prop": "eduPriem",
    "container_id": 10
  },
  {
    "id": 11,
    "item_prop": "eduPerevod",
    "container_id": 11
  },
  {
    "id": 12,
    "item_prop": "eduOp",
    "container_id": 12
  },
  {
    "id": 13,
    "item_prop": "eduAdOp",
    "container_id": 13
  },
  {
    "id": 14,
    "item_prop": "eduNir",
    "container_id": 14
  },
  {
    "id": 15,
    "item_prop": "",
    "container_id": 15
  },
  {
    "id": 16,
    "item_prop": "rucovodstvo",
    "container_id": 16
  },
  {
    "id": 17,
    "item_prop": "rucovodstvoZam",
    "container_id": 17
  },
  {
    "id": 18,
    "item_prop": "rucovodstvoFil",
    "container_id": 18
  },
  {
    "id": 19,
    "item_prop": "teachingStaff",
    "container_id": 19
  },
  {
    "id": 20,
    "item_prop": "",
    "container_id": 20
  },
  {
    "id": 21,
    "item_prop": "purposeCab",
    "container_id": 21
  },
  {
    "id": 22,
    "item_prop": "purposePrac",
    "container_id": 22
  },
  {
    "id": 23,
    "item_prop": "purposeLibr",
    "container_id": 23
  },
  {
    "id": 24,
    "item_prop": "purposeSport",
    "container_id": 24
  },
  {
    "id": 25,
    "item_prop": "meals",
    "container_id": 25
  },
  {
    "id": 26,
    "item_prop": "health",
    "container_id": 26
  },
  {
    "id": 27,
    "item_prop": "",
    "container_id": 27
  },
  {
    "id": 28,
    "item_prop": "graduateJob",
    "container_id": 28
  },
  {
    "id": 29,
    "item_prop": "",
    "container_id": 29
  },
  {
    "id": 30,
    "item_prop": "",
    "container_id": 30
  },
  {
    "id": 31,
    "item_prop": "volume",
    "container_id": 31
  },
  {
    "id": 32,
    "item_prop": "vacant",
    "container_id": 32
  },
  {
    "id": 33,
    "item_prop": "",
    "container_id": 33
  },
  {
    "id": 34,
    "item_prop": "purposeCab",
    "container_id": 34
  },
  {
    "id": 35,
    "item_prop": "purposePrac",
    "container_id": 35
  },
  {
    "id": 36,
    "item_prop": "purposeLibr",
    "container_id": 36
  },
  {
    "id": 37,
    "item_prop": "purposeSport",
    "container_id": 37
  },
  {
    "id": 38,
    "item_prop": "meals",
    "container_id": 38
  },
  {
    "id": 39,
    "item_prop": "health",
    "container_id": 39
  },
  {
    "id": 40,
    "item_prop": "internationalDog",
    "container_id": 40
  },
  {
    "id": 41,
    "item_prop": "internationalAccr",
    "container_id": 41
  }
]